{"cameraMode":{"drawMode":0,"name":"Shaded","section":"Shading Mode"},"sceneLighting":false,"audioPlay":false,"sceneViewState":{"m_AlwaysRefresh":false,"showFog":true,"showSkybox":false,"showFlares":true,"showImageEffects":true,"showParticleSystems":true,"showVisualEffectGraphs":true,"m_FxEnabled":true},"in2DMode":false,"pivot":{"x":0.0,"y":1.5068200826644898,"z":-1.0012500286102296},"rotation":{"x":-0.157649964094162,"y":0.1099558100104332,"z":-0.017666716128587724,"w":-0.9811967611312866},"size":1.498188853263855,"orthographic":false}