{"cameraMode":{"drawMode":0,"name":"Shaded","section":"Shading Mode"},"sceneLighting":false,"audioPlay":false,"sceneViewState":{"m_AlwaysRefresh":false,"showFog":true,"showSkybox":false,"showFlares":true,"showImageEffects":true,"showParticleSystems":true,"showVisualEffectGraphs":true,"m_FxEnabled":true},"in2DMode":false,"pivot":{"x":0.07424116879701615,"y":1.1365305185317994,"z":-0.14545975625514985},"rotation":{"x":-0.0009368151659145951,"y":-0.9848420023918152,"z":0.1734270453453064,"w":-0.005308099556714296},"size":0.9340226650238037,"orthographic":false}